python_cli_menu-1.8.1.dist-info/licenses/LICENSE.txt
pythonclimenu/__init__.py
pythonclimenu/climenu.py
tests/__init__.py
tests/ui_menu_test.py
python_cli_menu-1.8.1.dist-info/METADATA
python_cli_menu-1.8.1.dist-info/WHEEL
python_cli_menu-1.8.1.dist-info/top_level.txt
python_cli_menu-1.8.1.dist-info/RECORD
